renardo_reapy/__init__.py
renardo_reapy/__init__.pyi
renardo_reapy/__main__.py
renardo_reapy/__main__.pyi
renardo_reapy/additional_api.py
renardo_reapy/errors.py
renardo_reapy/errors.pyi
renardo_reapy/reascript_api.py
renardo_reapy/reascript_api.pyi
renardo_reapy/config/__init__.py
renardo_reapy/config/config.py
renardo_reapy/config/config.pyi
renardo_reapy/config/resource_path.py
renardo_reapy/config/shared_library.py
renardo_reapy/core/__init__.py
renardo_reapy/core/__init__.pyi
renardo_reapy/core/audio_accessor.py
renardo_reapy/core/audio_accessor.pyi
renardo_reapy/core/envelope.py
renardo_reapy/core/envelope.pyi
renardo_reapy/core/map.py
renardo_reapy/core/map.pyi
renardo_reapy/core/reapy_object.py
renardo_reapy/core/reapy_object.pyi
renardo_reapy/core/fx/__init__.py
renardo_reapy/core/fx/__init__.pyi
renardo_reapy/core/fx/fx.py
renardo_reapy/core/fx/fx.pyi
renardo_reapy/core/fx/fx_param.py
renardo_reapy/core/fx/fx_param.pyi
renardo_reapy/core/item/__init__.py
renardo_reapy/core/item/__init__.pyi
renardo_reapy/core/item/item.py
renardo_reapy/core/item/item.pyi
renardo_reapy/core/item/midi_event.py
renardo_reapy/core/item/midi_event.pyi
renardo_reapy/core/item/source.py
renardo_reapy/core/item/source.pyi
renardo_reapy/core/item/take.py
renardo_reapy/core/item/take.pyi
renardo_reapy/core/project/__init__.py
renardo_reapy/core/project/__init__.pyi
renardo_reapy/core/project/marker.py
renardo_reapy/core/project/marker.pyi
renardo_reapy/core/project/project.py
renardo_reapy/core/project/project.pyi
renardo_reapy/core/project/region.py
renardo_reapy/core/project/region.pyi
renardo_reapy/core/project/time_selection.py
renardo_reapy/core/project/time_selection.pyi
renardo_reapy/core/reaper/__init__.py
renardo_reapy/core/reaper/__init__.pyi
renardo_reapy/core/reaper/audio.py
renardo_reapy/core/reaper/audio.pyi
renardo_reapy/core/reaper/defer.py
renardo_reapy/core/reaper/defer.pyi
renardo_reapy/core/reaper/midi.py
renardo_reapy/core/reaper/midi.pyi
renardo_reapy-0.11.0.dev6.dist-info/METADATA
renardo_reapy-0.11.0.dev6.dist-info/WHEEL
renardo_reapy-0.11.0.dev6.dist-info/entry_points.txt
renardo_reapy-0.11.0.dev6.dist-info/RECORD
