Metadata-Version: 2.4
Name: renardo_reapy
Version: 0.11.0.dev6
Summary: A fork of Reapy, the pythonic wrapper for REAPER's ReaScript Python API. Intended to be refactored and simplifyed for maintenance and usage as base for renardo Reaper integration
Project-URL: Homepage, https://github.com/eliegavoty/renardo_reapy
Project-URL: Bug Tracker, https://github.com/eliegavoty/renardo_reapy/issues
Author-email: Roméo Després <mail.reapy@gmail.com>, Elie Gavoty <eliegavoty@free.fr>
Maintainer-email: Elie Gavoty <eliegavoty@free.fr>
License: MIT
Keywords: API,DAW,REAPER,ReaScript,audio,music,wrapper
Requires-Python: >=3.9
Requires-Dist: psutil
Requires-Dist: typing-extensions
